syncsonic/__init__.py
syncsonic/__main__.py
syncsonic/download.py
syncsonic-0.1.3.dist-info/METADATA
syncsonic-0.1.3.dist-info/WHEEL
syncsonic-0.1.3.dist-info/entry_points.txt
syncsonic-0.1.3.dist-info/licenses/LICENSE
syncsonic-0.1.3.dist-info/RECORD
