Metadata-Version: 2.4
Name: syncsonic
Version: 0.1.3
Summary: Download media from subsonic server for local playback and scrobble plays back to server 
Project-URL: Homepage, https://github.com/tepiloxtl/syncsonic
Project-URL: Issues, https://github.com/tepiloxtl/syncsonic/issues
Author-email: Tepiloxtl <tepiloxtl@tepiloxtl.net>
License-Expression: GPL-3.0-or-later
License-File: LICENSE
Classifier: Development Status :: 3 - Alpha
Classifier: Environment :: Console
Classifier: Operating System :: OS Independent
Classifier: Programming Language :: Python :: 3
Classifier: Programming Language :: Python :: 3.9
Classifier: Programming Language :: Python :: 3.10
Classifier: Programming Language :: Python :: 3.11
Requires-Python: >=3.9
Requires-Dist: requests
